chamfer_ext.cpython-39-darwin.so
chamfer/__init__.py
chamfer/src/kd_tree.cpp
chamfer/src/kd_tree.hpp
chamfer/src/metal_bridge.mm
torch_chamfer_dist-0.1.1.dist-info/licenses/LICENSE
torch_chamfer_dist-0.1.1.dist-info/METADATA
torch_chamfer_dist-0.1.1.dist-info/WHEEL
torch_chamfer_dist-0.1.1.dist-info/top_level.txt
torch_chamfer_dist-0.1.1.dist-info/RECORD
