Metadata-Version: 2.4
Name: torch-chamfer-dist
Version: 0.1.1
Summary: Chamfer distance with Metal/MPS acceleration (macOS)
Author: Janos
License-Expression: MIT
Project-URL: Homepage, https://github.com/Janos95/chamfer
Requires-Python: >=3.9
License-File: LICENSE
Requires-Dist: torch>=2.1
Requires-Dist: nanobind>=2.0
Dynamic: license-file
